setup.py
mongoengine_utils/__init__.py
mongoengine_utils/decoder.py
mongoengine_utils/document.py
mongoengine_utils/encoder.py
mongoengine_utils/fields.py
mongoengine_utils/queryset.py
mongoengine_utils.egg-info/PKG-INFO
mongoengine_utils.egg-info/SOURCES.txt
mongoengine_utils.egg-info/dependency_links.txt
mongoengine_utils.egg-info/not-zip-safe
mongoengine_utils.egg-info/requires.txt
mongoengine_utils.egg-info/top_level.txt