Metadata-Version: 1.1
Name: mongoengine-utils
Version: 1.0.1
Summary: More human readable JSON serializer/de-serializer, pagination for MongoEngine
Home-page: https://github.com/aiscenblue/mongoengine_utils
Author: Jeffrey Marvin Forones
Author-email: aiscenblue@gmail.com
License: MIT
Keywords: json mongoengine mongodb
Platform: UNKNOWN
Classifier: Programming Language :: Python :: 2.7
Classifier: Programming Language :: Python :: 3.5
